anc_maper.py
anc_maper-0.0.1.dist-info/LICENSE.txt
anc_maper-0.0.1.dist-info/METADATA
anc_maper-0.0.1.dist-info/WHEEL
anc_maper-0.0.1.dist-info/entry_points.txt
anc_maper-0.0.1.dist-info/top_level.txt
anc_maper-0.0.1.dist-info/RECORD
