Metadata-Version: 2.1
Name: anc-maper
Version: 0.0.1
Summary: Know the old names of prefectures
Home-page: https://github.com/yorunotuki/anc-maper
Author: ryo komatsu
Author-email: r.y.o627b@gmail.com
Project-URL: Bug Tracker, https://github.com/yorunotuki/anc-maper
Classifier: Programming Language :: Python :: 3
Classifier: License :: OSI Approved :: MIT License
Classifier: Operating System :: OS Independent
Requires-Python: >=3.12
License-File: LICENSE.txt
Requires-Dist: matplotlib >=3.9.0
Requires-Dist: japanmap >=0.3.1
